LICENSE
README.md
setup.py
congadocumentstatusservice/__init__.py
congadocumentstatusservice/document_status_service.py
congadocumentstatusservice.egg-info/PKG-INFO
congadocumentstatusservice.egg-info/SOURCES.txt
congadocumentstatusservice.egg-info/dependency_links.txt
congadocumentstatusservice.egg-info/top_level.txt