Metadata-Version: 2.1
Name: congadocumentstatusservice
Version: 0.0.3
Summary: A package change document process status for Conga core app
Home-page: https://github.com/nmarkovic-conga//conga-document-status-service/
Author: Nikola Markovic
Author-email: nmarkovic@conga.com
License: UNKNOWN
Platform: UNKNOWN
Classifier: Programming Language :: Python :: 3.9
Classifier: License :: OSI Approved :: GNU General Public License v3 (GPLv3)
License-File: LICENSE
